mitxpro_core/__init__.py
mitxpro_core/apps.py
mitxpro_core/middleware.py
mitxpro_core/middleware_test.py
mitxpro_core/settings/__init__.py
mitxpro_core/settings/common.py
mitxpro_core/settings/production.py
mitxpro_core/settings/test.py
mitxpro_core/urls.py
mitxpro_openedx_extensions-1.1.0.dist-info/LICENSE
mitxpro_openedx_extensions-1.1.0.dist-info/METADATA
mitxpro_openedx_extensions-1.1.0.dist-info/WHEEL
mitxpro_openedx_extensions-1.1.0.dist-info/entry_points.txt
mitxpro_openedx_extensions-1.1.0.dist-info/RECORD
